<?xml version="1.0"?>
<!--This file was created with the Microsoft Visual Programming Language.-->
<Manifest xmlns:simulatedtimer="http://brumba.ru/contracts/2012/10/simulatedtimer.html" xmlns:simulationtester="http://brumba.ru/contracts/2012/11/simulationtester.html" xmlns:simulation="http://schemas.microsoft.com/robotics/2006/04/simulation.html" xmlns:dssp="http://schemas.microsoft.com/xw/2004/10/dssp.html" xmlns:this="urn:uuid:974d2598-2dc0-42ac-8aac-fb9a300eec69" xmlns="http://schemas.microsoft.com/xw/2004/10/manifest.html">
  <CreateServiceList>
    <ServiceRecordType>
      <dssp:Contract>http://brumba.ru/contracts/2012/11/simulationtester.html</dssp:Contract>
      <dssp:PartnerList>
        <dssp:Partner>
          <dssp:Contract>http://brumba.ru/contracts/2012/11/simulationtester.html</dssp:Contract>
          <dssp:Service>simulationtester_visual.config.xml</dssp:Service>
          <dssp:PartnerList />
          <dssp:Name>dssp:StateService</dssp:Name>
        </dssp:Partner>
        <dssp:Partner>
          <dssp:Contract>http://brumba.ru/contracts/2012/10/simulatedtimer.html</dssp:Contract>
          <dssp:PartnerList />
          <dssp:Name>simulationtester:SimTimer</dssp:Name>
          <dssp:ServiceName>this:SimulatedTimerService</dssp:ServiceName>
        </dssp:Partner>
      </dssp:PartnerList>
      <Name>this:simulationtester</Name>
    </ServiceRecordType>
    <ServiceRecordType>
      <dssp:Contract>http://brumba.ru/contracts/2012/10/simulatedtimer.html</dssp:Contract>
      <dssp:PartnerList>
        <dssp:Partner>
          <dssp:Service>http://localhost/timer</dssp:Service>
          <dssp:PartnerList />
          <dssp:Name>simulation:Entity</dssp:Name>
        </dssp:Partner>
      </dssp:PartnerList>
      <Name>this:SimulatedTimerService</Name>
    </ServiceRecordType>
  </CreateServiceList>
</Manifest>